HISTORY.txt
MANIFEST.in
Makefile
README.rst
bootstrap.py
plone40.cfg
plone41.cfg
plone42.cfg
plone43.cfg
plone50.cfg
setup.py
Products/__init__.py
Products.PTProfiler.egg-info/PKG-INFO
Products.PTProfiler.egg-info/SOURCES.txt
Products.PTProfiler.egg-info/dependency_links.txt
Products.PTProfiler.egg-info/namespace_packages.txt
Products.PTProfiler.egg-info/not-zip-safe
Products.PTProfiler.egg-info/requires.txt
Products.PTProfiler.egg-info/top_level.txt
Products/PTProfiler/CREDITS.txt
Products/PTProfiler/INSTALL.txt
Products/PTProfiler/LICENSE.txt
Products/PTProfiler/PTProfilerViewer.py
Products/PTProfiler/ProfileContainer.py
Products/PTProfiler/ProfilerPatch.py
Products/PTProfiler/__init__.py
Products/PTProfiler/testing.py
Products/PTProfiler/version.txt
Products/PTProfiler/tests/__init__.py
Products/PTProfiler/tests/test_install.py
Products/PTProfiler/www/PTP.gif
Products/PTProfiler/www/PTProfilerViewTab.zpt
Products/PTProfiler/www/addPTProfilerViewer.zpt