Metadata-Version: 1.1
Name: Products.PTProfiler
Version: 1.5
Summary: PageTemplate profiler for Zope 2
Home-page: https://github.com/infrae/Products.PTProfiler
Author: Guido Wesdorp and Infrae
Author-email: info@infrae.com
License: BSD
Keywords: zope2 page template profiler
Platform: UNKNOWN
Classifier: Framework :: Zope2
Classifier: License :: OSI Approved :: BSD License
Classifier: Programming Language :: Python
Classifier: Programming Language :: Python :: 2.6
Classifier: Programming Language :: Python :: 2.7
Classifier: Topic :: Software Development :: Libraries :: Python Modules
